pyqt_fitting_graphics_view/__init__.py
pyqt_fitting_graphics_view/fittingGraphicsView.py
pyqt_fitting_graphics_view-0.0.12.dist-info/LICENSE
pyqt_fitting_graphics_view-0.0.12.dist-info/METADATA
pyqt_fitting_graphics_view-0.0.12.dist-info/WHEEL
pyqt_fitting_graphics_view-0.0.12.dist-info/top_level.txt
pyqt_fitting_graphics_view-0.0.12.dist-info/RECORD
