Metadata-Version: 2.1
Name: pyqt-fitting-graphics-view
Version: 0.0.12
Summary: PyQt QGraphicsView which always fit the aspect ratio mode as Qt.KeepAspectRatio
Home-page: https://github.com/yjg30737/pyqt-fitting-graphics-view.git
Author: Jung Gyu Yoon
Author-email: yjg30737@gmail.com
License: MIT
Platform: UNKNOWN
License-File: LICENSE
Requires-Dist: PyQt5 (>=5.8)
Requires-Dist: pyqt-single-image-graphics-view (>=0.0.1)
